README.md
setup.cfg
setup.py
db_sheet/__init__.py
db_sheet/db_sheet.py
db_sheet/sheet_table.py
db_sheet.egg-info/PKG-INFO
db_sheet.egg-info/SOURCES.txt
db_sheet.egg-info/dependency_links.txt
db_sheet.egg-info/requires.txt
db_sheet.egg-info/top_level.txt